tests/__init__.py
tests/test_metrics.py
universal_tsdb/__init__.py
universal_tsdb/exceptions.py
universal_tsdb/metrics.py
universal_tsdb-0.1.1.dist-info/LICENSE
universal_tsdb-0.1.1.dist-info/METADATA
universal_tsdb-0.1.1.dist-info/WHEEL
universal_tsdb-0.1.1.dist-info/top_level.txt
universal_tsdb-0.1.1.dist-info/RECORD
