Metadata-Version: 2.1
Name: universal-tsdb
Version: 0.1.1
Summary: A Universal Time-Series Database Python Client
Home-page: https://github.com/gmasse/universal-tsdb
Author: Germain Masse
Author-email: g-dev@masse.me
License: UNKNOWN
Keywords: timeseries-database,time-series,python,influxdb,warp10
Platform: UNKNOWN
Classifier: Development Status :: 4 - Beta
Classifier: License :: OSI Approved :: GNU General Public License v3 (GPLv3)
Classifier: Programming Language :: Python :: 3
Classifier: Intended Audience :: Developers
Classifier: Intended Audience :: Information Technology
Classifier: Intended Audience :: Science/Research
Classifier: Topic :: Software Development :: Libraries :: Python Modules
Classifier: Natural Language :: English
Requires-Python: >=3.6
Requires-Dist: requests
Provides-Extra: dev
Requires-Dist: pylint ; extra == 'dev'
Requires-Dist: pytest ; extra == 'dev'
